{"id":"2023-clearly-donruss-football","name":"2023 Clearly Donruss Football","year":2023,"brand":"Clearly Donruss","sport":"Football","sets":[{"id":"base-set","name":"Base Set","category":"base","totalCards":100,"parallels":[{"name":"Gold","printRun":null},{"name":"Mosaic Holo","printRun":null},{"name":"Purple","printRun":199},{"name":"Blue","printRun":99},{"name":"Orange","printRun":75},{"name":"Red","printRun":49},{"name":"Green","printRun":25},{"name":"Black","printRun":10},{"name":"Pink","printRun":10},{"name":"Techno","printRun":10},{"name":"Gold Holo","printRun":5},{"name":"Black Spider","printRun":1},{"name":"Platinum Holo","printRun":1}],"cards":[{"number":"1","player":"James Conner","team":"Arizona Cardinals"},{"number":"2","player":"Desmond Ridder","team":"Atlanta Falcons"},{"number":"3","player":"Drake London","team":"Atlanta Falcons"},{"number":"4","player":"Odell Beckham Jr.","team":"Baltimore Ravens"},{"number":"5","player":"Patrick Queen","team":"Baltimore Ravens"},{"number":"6","player":"James Cook","team":"Buffalo Bills"},{"number":"7","player":"Josh Allen","team":"Buffalo Bills"},{"number":"8","player":"Brian Burns","team":"Carolina Panthers"},{"number":"9","player":"Miles Sanders","team":"Carolina Panthers"},{"number":"10","player":"Justin Fields","team":"Chicago Bears"},{"number":"11","player":"Joe Burrow","team":"Cincinnati Bengals"},{"number":"12","player":"Ja’Marr Chase","team":"Cincinnati Bengals"},{"number":"13","player":"Amari Cooper","team":"Cleveland Browns"},{"number":"14","player":"Dak Prescott","team":"Dallas Cowboys"},{"number":"15","player":"Micah Parsons","team":"Dallas Cowboys"},{"number":"16","player":"Javonte Williams","team":"Denver Broncos"},{"number":"17","player":"Amon-Ra St. Brown","team":"Detroit Lions"},{"number":"18","player":"Jared Goff","team":"Detroit Lions"},{"number":"19","player":"Jordan Love","team":"Green Bay Packers"},{"number":"20","player":"Romeo Doubs","team":"Green Bay Packers"},{"number":"21","player":"Dameon Pierce","team":"Houston Texans"},{"number":"22","player":"DeForest Buckner","team":"Indianapolis Colts"},{"number":"23","player":"Trevor Lawrence","team":"Jacksonville Jaguars"},{"number":"24","player":"Evan Engram","team":"Jacksonville Jaguars"},{"number":"25","player":"Patrick Mahomes II","team":"Kansas City Chiefs"},{"number":"26","player":"Travis Kelce","team":"Kansas City Chiefs"},{"number":"27","player":"Davante Adams","team":"Las Vegas Raiders"},{"number":"28","player":"Austin Ekeler","team":"Los Angeles Chargers"},{"number":"29","player":"Justin Herbert","team":"Los Angeles Chargers"},{"number":"30","player":"Kyren Williams","team":"Los Angeles Rams"},{"number":"31","player":"Tua Tagovailoa","team":"Miami Dolphins"},{"number":"32","player":"Tyreek Hill","team":"Miami Dolphins"},{"number":"33","player":"Kirk Cousins","team":"Minnesota Vikings"},{"number":"34","player":"Justin Jefferson","team":"Minnesota Vikings"},{"number":"35","player":"Chris Olave","team":"New Orleans Saints"},{"number":"36","player":"Saquon Barkley","team":"New York Giants"},{"number":"37","player":"Garrett Wilson","team":"New York Jets"},{"number":"38","player":"Aaron Rodgers","team":"New York Jets"},{"number":"39","player":"D’Andre Swift","team":"Philadelphia Eagles"},{"number":"40","player":"Jalen Hurts","team":"Philadelphia Eagles"},{"number":"41","player":"George Pickens","team":"Pittsburgh Steelers"},{"number":"42","player":"T.J. Watt","team":"Pittsburgh Steelers"},{"number":"43","player":"Brock Purdy","team":"San Francisco 49ers"},{"number":"44","player":"Nick Bosa","team":"San Francisco 49ers"},{"number":"45","player":"Tyler Lockett","team":"Seattle Seahawks"},{"number":"46","player":"Baker Mayfield","team":"Tampa Bay Buccaneers"},{"number":"47","player":"Ryan Tannehill","team":"Tennessee Titans"},{"number":"48","player":"Derrick Henry","team":"Tennessee Titans"},{"number":"49","player":"Brian Robinson Jr.","team":"Washington Commanders"},{"number":"50","player":"Sam Howell","team":"Washington Commanders"}]},{"id":"rated-rookies","name":"Rated Rookies","category":"base","totalCards":50,"parallels":[{"name":"Gold","printRun":null},{"name":"Mosaic Holo","printRun":null},{"name":"RR Logo Holo","printRun":null},{"name":"Purple","printRun":199},{"name":"Blue","printRun":99},{"name":"Orange","printRun":75},{"name":"Red","printRun":49},{"name":"Green","printRun":25},{"name":"Black","printRun":10},{"name":"Pink","printRun":10},{"name":"Techno","printRun":10},{"name":"Gold Holo","printRun":5},{"name":"Black Spider","printRun":1},{"name":"Platinum Holo","printRun":1}],"cards":[{"number":"51","player":"Aidan O’Connell","team":"Las Vegas Raiders"},{"number":"52","player":"Anthony Richardson","team":"Indianapolis Colts"},{"number":"53","player":"Bijan Robinson","team":"Atlanta Falcons"},{"number":"54","player":"Cedric Tillman","team":"Cleveland Browns"},{"number":"55","player":"Chase Brown","team":"Cincinnati Bengals"},{"number":"56","player":"Clayton Tune","team":"Arizona Cardinals"},{"number":"57","player":"Dalton Kincaid","team":"Buffalo Bills"},{"number":"58","player":"Deuce Vaughn","team":"Dallas Cowboys"},{"number":"59","player":"De’Von Achane","team":"Miami Dolphins"},{"number":"60","player":"Dorian Thompson-Robinson","team":"Cleveland Browns"},{"number":"61","player":"Hendon Hooker","team":"Detroit Lions"},{"number":"62","player":"Jahmyr Gibbs","team":"Detroit Lions"},{"number":"63","player":"Jake Haener","team":"New Orleans Saints"},{"number":"64","player":"Jalen Carter","team":"Philadelphia Eagles"},{"number":"65","player":"Jalin Hyatt","team":"New York Giants"},{"number":"66","player":"Jaren Hall","team":"Minnesota Vikings"},{"number":"67","player":"Jaxon Smith-Njigba","team":"Seattle Seahawks"},{"number":"68","player":"Jayden Reed","team":"Green Bay Packers"},{"number":"69","player":"Jonathan Mingo","team":"Carolina Panthers"},{"number":"70","player":"Jordan Addison","team":"Minnesota Vikings"},{"number":"71","player":"Josh Downs","team":"Indianapolis Colts"},{"number":"72","player":"Kendre Miller","team":"New Orleans Saints"},{"number":"73","player":"Luke Schoonmaker","team":"Dallas Cowboys"},{"number":"74","player":"Marvin Mims","team":"Denver Broncos"},{"number":"75","player":"Michael Mayer","team":"Las Vegas Raiders"},{"number":"76","player":"Michael Wilson","team":"Arizona Cardinals"},{"number":"77","player":"Parker Washington","team":"Jacksonville Jaguars"},{"number":"78","player":"Quentin Johnston","team":"Los Angeles Chargers"},{"number":"79","player":"Rashee Rice","team":"Kansas City Chiefs"},{"number":"80","player":"Roschon Johnson","team":"Chicago Bears"},{"number":"81","player":"Sam LaPorta","team":"Detroit Lions"},{"number":"82","player":"Sean Clifford","team":"Green Bay Packers"},{"number":"83","player":"Stetson Bennett IV","team":"Los Angeles Rams"},{"number":"84","player":"Tank Bigsby","team":"Jacksonville Jaguars"},{"number":"85","player":"Tank Dell","team":"Houston Texans"},{"number":"86","player":"Tanner McKee","team":"Philadelphia Eagles"},{"number":"87","player":"Tre Tucker","team":"Las Vegas Raiders"},{"number":"88","player":"Tyjae Spears","team":"Tennessee Titans"},{"number":"89","player":"Tyler Scott","team":"Chicago Bears"},{"number":"90","player":"Will Anderson Jr.","team":"Houston Texans"},{"number":"91","player":"Zach Charbonnet","team":"Seattle Seahawks"},{"number":"92","player":"Zay Flowers","team":"Baltimore Ravens"},{"number":"93","player":"C.J. Stroud","team":"Houston Texans"},{"number":"94","player":"Will Levis","team":"Tennessee Titans"},{"number":"95","player":"Bryce Young","team":"Carolina Panthers"},{"number":"96","player":"Puka Nacua","team":"Los Angeles Rams"},{"number":"97","player":"Tommy DeVito","team":"New York Giants"},{"number":"98","player":"Christian Gonzalez","team":"New England Patriots"},{"number":"99","player":"Devon Witherspoon","team":"Seattle Seahawks"},{"number":"100","player":"Tyson Bagent","team":"Chicago Bears"}]},{"id":"base-autographs","name":"Base Autographs","category":"autograph","totalCards":15,"parallels":[{"name":"Base","printRun":null}],"cards":[{"number":"5","player":"Patrick Queen","team":"Baltimore Ravens","printRun":200},{"number":"6","player":"James Cook","team":"Buffalo Bills","printRun":200},{"number":"8","player":"Brian Burns","team":"Carolina Panthers","printRun":100},{"number":"10","player":"Justin Fields","team":"Chicago Bears","printRun":200},{"number":"16","player":"Javonte Williams","team":"Denver Broncos","printRun":25},{"number":"17","player":"Amon-Ra St. Brown","team":"Detroit Lions","printRun":50},{"number":"20","player":"Romeo Doubs","team":"Green Bay Packers","printRun":50},{"number":"29","player":"Justin Herbert","team":"Los Angeles Chargers","printRun":25},{"number":"30","player":"Kyren Williams","team":"Los Angeles Rams","printRun":200},{"number":"34","player":"Justin Jefferson","team":"Minnesota Vikings","printRun":50},{"number":"41","player":"George Pickens","team":"Pittsburgh Steelers","printRun":200},{"number":"43","player":"Brock Purdy","team":"San Francisco 49ers","printRun":25},{"number":"46","player":"Baker Mayfield","team":"Tampa Bay Buccaneers","printRun":50},{"number":"49","player":"Brian Robinson Jr.","team":"Washington Commanders","printRun":200},{"number":"50","player":"Sam Howell","team":"Washington Commanders","printRun":50}]},{"id":"clearly-champions-autographs","name":"Clearly Champions Autographs","category":"autograph","totalCards":6,"parallels":[{"name":"Base","printRun":null}],"cards":[{"number":"2","player":"Andy Reid","team":"Kansas City Chiefs","printRun":25},{"number":"7","player":"Nick Bolton","team":"Kansas City Chiefs","printRun":100},{"number":"8","player":"Harrison Butker","team":"Kansas City Chiefs","printRun":100},{"number":"10","player":"Marquez Valdes-Scantling","team":"Kansas City Chiefs","printRun":100},{"number":"11","player":"Skyy Moore","team":"Kansas City Chiefs","printRun":100},{"number":"14","player":"Tommy Townsend","team":"Kansas City Chiefs","printRun":100}]},{"id":"clearly-highlights-autographs","name":"Clearly Highlights Autographs","category":"autograph","totalCards":6,"parallels":[{"name":"Base","printRun":null}],"cards":[{"number":"1","player":"Justin Fields","team":"Chicago Bears","printRun":100},{"number":"3","player":"Deebo Samuel","team":"San Francisco 49ers","printRun":25},{"number":"4","player":"Justin Jefferson","team":"Minnesota Vikings","printRun":50},{"number":"7","player":"Jerry Jeudy","team":"Denver Broncos","printRun":50},{"number":"10","player":"Van Jefferson","team":"Los Angeles Rams","printRun":25},{"number":"12","player":"DJ Moore","team":"Carolina Panthers","printRun":25}]},{"id":"clearly-my-house-autographs","name":"Clearly My House Autographs","category":"autograph","totalCards":6,"parallels":[{"name":"Base","printRun":null}],"cards":[{"number":"4","player":"CeeDee Lamb","team":"Dallas Cowboys","printRun":25},{"number":"5","player":"Justin Jefferson","team":"Minnesota Vikings","printRun":25},{"number":"6","player":"Aaron Rodgers","team":"New York Jets","printRun":10},{"number":"7","player":"Nick Chubb","team":"Cleveland Browns","printRun":25},{"number":"8","player":"Josh Jacobs","team":"Las Vegas Raiders","printRun":25},{"number":"9","player":"Justin Herbert","team":"Los Angeles Chargers","printRun":10}]},{"id":"clearly-rated-rookie-autographs","name":"Clearly Rated Rookie Autographs","category":"autograph","totalCards":47,"parallels":[{"name":"Mosaic Holo","printRun":null},{"name":"RR Logo Holo","printRun":null},{"name":"Purple – /175 (no Mayer)","printRun":null},{"name":"Blue – /99 (no 75 Mayer)","printRun":null},{"name":"Orange","printRun":75},{"name":"Red","printRun":49},{"name":"Pink","printRun":15},{"name":"Green","printRun":25},{"name":"Vintage Stripes","printRun":18},{"name":"Black","printRun":10},{"name":"Techno","printRun":10},{"name":"Gold Holo","printRun":5},{"name":"Black Spider","printRun":1},{"name":"Platinum Holo","printRun":1}],"cards":[{"number":"51","player":"Aidan O’Connell","team":"Las Vegas Raiders"},{"number":"52","player":"Anthony Richardson","team":"Indianapolis Colts"},{"number":"53","player":"Bijan Robinson","team":"Atlanta Falcons"},{"number":"54","player":"Cedric Tillman","team":"Cleveland Browns"},{"number":"55","player":"Chase Brown","team":"Cincinnati Bengals"},{"number":"56","player":"Clayton Tune","team":"Arizona Cardinals"},{"number":"57","player":"Dalton Kincaid","team":"Buffalo Bills"},{"number":"58","player":"Deuce Vaughn","team":"Dallas Cowboys"},{"number":"59","player":"De’Von Achane","team":"Miami Dolphins"},{"number":"60","player":"Dorian Thompson-Robinson","team":"Cleveland Browns"},{"number":"61","player":"Hendon Hooker","team":"Detroit Lions"},{"number":"62","player":"Jahmyr Gibbs","team":"Detroit Lions"},{"number":"63","player":"Jake Haener","team":"New Orleans Saints"},{"number":"64","player":"Jalen Carter","team":"Philadelphia Eagles"},{"number":"65","player":"Jalin Hyatt","team":"New York Giants"},{"number":"66","player":"Jaren Hall","team":"Minnesota Vikings"},{"number":"67","player":"Jaxon Smith-Njigba","team":"Seattle Seahawks"},{"number":"68","player":"Jayden Reed","team":"Green Bay Packers"},{"number":"69","player":"Jonathan Mingo","team":"Carolina Panthers"},{"number":"70","player":"Jordan Addison","team":"Minnesota Vikings"},{"number":"71","player":"Josh Downs","team":"Indianapolis Colts"},{"number":"72","player":"Kendre Miller","team":"New Orleans Saints"},{"number":"73","player":"Luke Schoonmaker","team":"Dallas Cowboys"},{"number":"74","player":"Marvin Mims","team":"Denver Broncos"},{"number":"75","player":"Michael Mayer","team":"Las Vegas Raiders"},{"number":"76","player":"Michael Wilson","team":"Arizona Cardinals"},{"number":"77","player":"Parker Washington","team":"Jacksonville Jaguars"},{"number":"78","player":"Quentin Johnston","team":"Los Angeles Chargers"},{"number":"79","player":"Rashee Rice","team":"Kansas City Chiefs"},{"number":"80","player":"Roschon Johnson","team":"Chicago Bears"},{"number":"81","player":"Sam LaPorta","team":"Detroit Lions"},{"number":"82","player":"Sean Clifford","team":"Green Bay Packers"},{"number":"83","player":"Stetson Bennett IV","team":"Los Angeles Rams"},{"number":"84","player":"Tank Bigsby","team":"Jacksonville Jaguars"},{"number":"85","player":"Tank Dell","team":"Houston Texans"},{"number":"86","player":"Tanner McKee","team":"Philadelphia Eagles"},{"number":"87","player":"Tre Tucker","team":"Las Vegas Raiders"},{"number":"88","player":"Tyjae Spears","team":"Tennessee Titans"},{"number":"89","player":"Tyler Scott","team":"Chicago Bears"},{"number":"90","player":"Will Anderson Jr.","team":"Houston Texans"},{"number":"91","player":"Zach Charbonnet","team":"Seattle Seahawks"},{"number":"92","player":"Zay Flowers","team":"Baltimore Ravens"},{"number":"96","player":"Puka Nacua","team":"Los Angeles Rams"},{"number":"97","player":"Tommy DeVito","team":"New York Giants"},{"number":"98","player":"Christian Gonzalez","team":"New England Patriots"},{"number":"99","player":"Devon Witherspoon","team":"Seattle Seahawks"},{"number":"100","player":"Tyson Bagent","team":"Chicago Bears"}]},{"id":"clearly-retro-1993-autographs","name":"Clearly Retro 1993 Autographs","category":"autograph","totalCards":8,"parallels":[{"name":"Base","printRun":null}],"cards":[{"number":"4","player":"Travis Etienne Jr.","team":"Jacksonville Jaguars","printRun":25},{"number":"6","player":"Justin Herbert","team":"Los Angeles Chargers","printRun":5},{"number":"8","player":"Mac Jones","team":"New England Patriots","printRun":25},{"number":"9","player":"Cooper Kupp","team":"Los Angeles Rams","printRun":25},{"number":"13","player":"Nick Chubb","team":"Cleveland Browns","printRun":25},{"number":"14","player":"Deebo Samuel","team":"San Francisco 49ers","printRun":25},{"number":"19","player":"Puka Nacua","team":"Los Angeles Rams","printRun":25},{"number":"20","player":"Brock Purdy","team":"San Francisco 49ers","printRun":25}]},{"id":"clearly-retro-2003-autographs","name":"Clearly Retro 2003 Autographs","category":"autograph","totalCards":18,"parallels":[{"name":"Base","printRun":null}],"cards":[{"number":"1","player":"Amani Toomer","team":"New York Giants","printRun":100},{"number":"2","player":"Brian Urlacher","team":"Chicago Bears","printRun":25},{"number":"3","player":"Clinton Portis","team":"Denver Broncos","printRun":100},{"number":"4","player":"Daunte Culpepper","team":"Minnesota Vikings","printRun":25},{"number":"5","player":"Deuce McAllister","team":"New Orleans Saints","printRun":25},{"number":"6","player":"Ed Reed","team":"Baltimore Ravens","printRun":25},{"number":"7","player":"Eddie George","team":"Tennessee Titans","printRun":50},{"number":"8","player":"Emmitt Smith","team":"Dallas Cowboys","printRun":25},{"number":"10","player":"Jake Plummer","team":"Arizona Cardinals","printRun":100},{"number":"11","player":"Jason Taylor","team":"Miami Dolphins","printRun":50},{"number":"12","player":"Julius Peppers","team":"Carolina Panthers","printRun":25},{"number":"13","player":"Jimmy Smith","team":"Jacksonville Jaguars","printRun":25},{"number":"14","player":"Michael Vick","team":"Atlanta Falcons","printRun":100},{"number":"15","player":"Doug Flutie","team":"New England Patriots","printRun":25},{"number":"17","player":"Ricky Williams","team":"Miami Dolphins","printRun":25},{"number":"18","player":"Jason Sehorn","team":"New York Giants","printRun":25},{"number":"19","player":"Kordell Stewart","team":"Pittsburgh Steelers","printRun":25},{"number":"20","player":"Leroy Kelly","team":"Cleveland Browns","printRun":100}]},{"id":"clearly-the-rookies-autographs","name":"Clearly The Rookies Autographs","category":"autograph","totalCards":12,"parallels":[{"name":"Base","printRun":null}],"cards":[{"number":"1","player":"Anthony Richardson","team":"Indianapolis Colts","printRun":25},{"number":"2","player":"Bijan Robinson","team":"Atlanta Falcons","printRun":25},{"number":"3","player":"Jahmyr Gibbs","team":"Detroit Lions","printRun":25},{"number":"4","player":"Jaxon Smith-Njigba","team":"Seattle Seahawks","printRun":25},{"number":"5","player":"Quentin Johnston","team":"Los Angeles Chargers","printRun":25},{"number":"6","player":"Zay Flowers","team":"Baltimore Ravens","printRun":25},{"number":"7","player":"Jordan Addison","team":"Minnesota Vikings","printRun":25},{"number":"8","player":"Hendon Hooker","team":"Detroit Lions","printRun":25},{"number":"9","player":"Puka Nacua","team":"Los Angeles Rams","printRun":25},{"number":"10","player":"Jayden Reed","team":"Green Bay Packers","printRun":25},{"number":"11","player":"Rashee Rice","team":"Kansas City Chiefs","printRun":25},{"number":"15","player":"De’Von Achane","team":"Miami Dolphins","printRun":25}]},{"id":"clearly-champions","name":"Clearly Champions","category":"insert","totalCards":15,"parallels":[{"name":"Mosaic Holo","printRun":null},{"name":"Red","printRun":100},{"name":"Green","printRun":49},{"name":"Silver Holo","printRun":25},{"name":"Gold Holo","printRun":10},{"name":"Platinum Holo","printRun":1}],"cards":[{"number":"1","player":"Patrick Mahomes II","team":"Kansas City Chiefs"},{"number":"2","player":"Andy Reid","team":"Kansas City Chiefs"},{"number":"3","player":"Isiah Pacheco","team":"Kansas City Chiefs"},{"number":"4","player":"Jerick McKinnon","team":"Kansas City Chiefs"},{"number":"5","player":"Travis Kelce","team":"Kansas City Chiefs"},{"number":"6","player":"Chris Jones","team":"Kansas City Chiefs"},{"number":"7","player":"Nick Bolton","team":"Kansas City Chiefs"},{"number":"8","player":"Harrison Butker","team":"Kansas City Chiefs"},{"number":"9","player":"Frank Clark","team":"Kansas City Chiefs"},{"number":"10","player":"Marquez Valdes-Scantling","team":"Kansas City Chiefs"},{"number":"11","player":"Skyy Moore","team":"Kansas City Chiefs"},{"number":"12","player":"JuJu Smith-Schuster","team":"Kansas City Chiefs"},{"number":"13","player":"Justin Watson","team":"Kansas City Chiefs"},{"number":"14","player":"Tommy Townsend","team":"Kansas City Chiefs"},{"number":"15","player":"Kadarius Toney","team":"Kansas City Chiefs"}]},{"id":"clearly-highlights","name":"Clearly Highlights","category":"insert","totalCards":12,"parallels":[{"name":"Mosaic Holo","printRun":null},{"name":"Red","printRun":100},{"name":"Green","printRun":49},{"name":"Silver Holo","printRun":25},{"name":"Gold Holo","printRun":10},{"name":"Platinum Holo","printRun":1}],"cards":[{"number":"1","player":"Justin Fields","team":"Chicago Bears"},{"number":"2","player":"Kirk Cousins","team":"Minnesota Vikings"},{"number":"3","player":"Deebo Samuel","team":"San Francisco 49ers"},{"number":"4","player":"Justin Jefferson","team":"Minnesota Vikings"},{"number":"5","player":"Mike Williams","team":"Los Angeles Chargers"},{"number":"6","player":"Ja’Marr Chase","team":"Cincinnati Bengals"},{"number":"7","player":"Jerry Jeudy","team":"Denver Broncos"},{"number":"8","player":"Josh Jacobs","team":"Las Vegas Raiders"},{"number":"9","player":"Patrick Mahomes II","team":"Kansas City Chiefs"},{"number":"10","player":"Van Jefferson","team":"Los Angeles Rams"},{"number":"11","player":"Jalen Hurts","team":"Philadelphia Eagles"},{"number":"12","player":"DJ Moore","team":"Carolina Panthers"}]},{"id":"clearly-my-house","name":"Clearly My House","category":"insert","totalCards":14,"parallels":[{"name":"Mosaic Holo","printRun":null},{"name":"Red","printRun":100},{"name":"Green","printRun":49},{"name":"Silver Holo","printRun":25},{"name":"Gold Holo","printRun":10},{"name":"Platinum Holo","printRun":1}],"cards":[{"number":"1","player":"Patrick Mahomes II","team":"Kansas City Chiefs"},{"number":"2","player":"Jalen Hurts","team":"Philadelphia Eagles"},{"number":"3","player":"Ahmad “Sauce” Gardner","team":"New York Jets"},{"number":"4","player":"CeeDee Lamb","team":"Dallas Cowboys"},{"number":"5","player":"Justin Jefferson","team":"Minnesota Vikings"},{"number":"6","player":"Aaron Rodgers","team":"New York Jets"},{"number":"7","player":"Nick Chubb","team":"Cleveland Browns"},{"number":"8","player":"Josh Jacobs","team":"Las Vegas Raiders"},{"number":"9","player":"Justin Herbert","team":"Los Angeles Chargers"},{"number":"10","player":"D’Andre Swift","team":"Philadelphia Eagles"},{"number":"11","player":"Austin Ekeler","team":"Los Angeles Chargers"},{"number":"12","player":"C.J. Stroud","team":"Houston Texans"},{"number":"13","player":"Bryce Young","team":"Carolina Panthers"},{"number":"14","player":"Will Levis","team":"Tennessee Titans"}]},{"id":"clearly-retro-1993","name":"Clearly Retro 1993","category":"insert","totalCards":20,"parallels":[{"name":"Mosaic Holo","printRun":null},{"name":"Red","printRun":100},{"name":"Green","printRun":49},{"name":"Silver Holo","printRun":25},{"name":"Gold Holo","printRun":10},{"name":"Platinum Holo","printRun":1}],"cards":[{"number":"1","player":"Micah Parsons","team":"Dallas Cowboys"},{"number":"2","player":"Chris Olave","team":"New Orleans Saints"},{"number":"3","player":"Joey Bosa","team":"Los Angeles Chargers"},{"number":"4","player":"Travis Etienne Jr.","team":"Jacksonville Jaguars"},{"number":"5","player":"Davante Adams","team":"Las Vegas Raiders"},{"number":"6","player":"Justin Herbert","team":"Los Angeles Chargers"},{"number":"7","player":"Ahmad “Sauce” Gardner","team":"New York Jets"},{"number":"8","player":"Mac Jones","team":"New England Patriots"},{"number":"9","player":"Cooper Kupp","team":"Los Angeles Rams"},{"number":"10","player":"Matt Judon","team":"New England Patriots"},{"number":"11","player":"Kirk Cousins","team":"Minnesota Vikings"},{"number":"12","player":"Miles Sanders","team":"Carolina Panthers"},{"number":"13","player":"Nick Chubb","team":"Cleveland Browns"},{"number":"14","player":"Deebo Samuel","team":"San Francisco 49ers"},{"number":"15","player":"Derrick Henry","team":"Tennessee Titans"},{"number":"16","player":"Bryce Young","team":"Carolina Panthers"},{"number":"17","player":"Will Levis","team":"Tennessee Titans"},{"number":"18","player":"C.J. Stroud","team":"Houston Texans"},{"number":"19","player":"Puka Nacua","team":"Los Angeles Rams"},{"number":"20","player":"Brock Purdy","team":"San Francisco 49ers"}]},{"id":"clearly-retro-2003","name":"Clearly Retro 2003","category":"insert","totalCards":20,"parallels":[{"name":"Mosaic Holo","printRun":null},{"name":"Red","printRun":100},{"name":"Green","printRun":49},{"name":"Silver Holo","printRun":25},{"name":"Gold Holo","printRun":10},{"name":"Platinum Holo","printRun":1}],"cards":[{"number":"1","player":"Amani Toomer","team":"New York Giants"},{"number":"2","player":"Brian Urlacher","team":"Chicago Bears"},{"number":"3","player":"Clinton Portis","team":"Denver Broncos"},{"number":"4","player":"Daunte Culpepper","team":"Minnesota Vikings"},{"number":"5","player":"Deuce McAllister","team":"New Orleans Saints"},{"number":"6","player":"Ed Reed","team":"Baltimore Ravens"},{"number":"7","player":"Eddie George","team":"Tennessee Titans"},{"number":"8","player":"Emmitt Smith","team":"Dallas Cowboys"},{"number":"9","player":"Isaac Bruce","team":"St. Louis Rams"},{"number":"10","player":"Jake Plummer","team":"Arizona Cardinals"},{"number":"11","player":"Jason Taylor","team":"Miami Dolphins"},{"number":"12","player":"Julius Peppers","team":"Carolina Panthers"},{"number":"13","player":"Jimmy Smith","team":"Jacksonville Jaguars"},{"number":"14","player":"Michael Vick","team":"Atlanta Falcons"},{"number":"15","player":"Doug Flutie","team":"New England Patriots"},{"number":"16","player":"Rich Gannon","team":"Oakland Raiders"},{"number":"17","player":"Ricky Williams","team":"Miami Dolphins"},{"number":"18","player":"Jason Sehorn","team":"New York Giants"},{"number":"19","player":"Kordell Stewart","team":"Pittsburgh Steelers"},{"number":"20","player":"Leroy Kelly","team":"Cleveland Browns"}]},{"id":"clearly-retro-rated-rookie-1988","name":"Clearly Retro Rated Rookie 1988","category":"insert","totalCards":3,"parallels":[{"name":"Platinum Holo","printRun":1}],"cards":[{"number":"1","player":"Bryce Young","team":"Carolina Panthers"},{"number":"2","player":"C.J. Stroud","team":"Houston Texans"},{"number":"3","player":"Will Levis","team":"Tennessee Titans"}]},{"id":"clearly-retro-rated-rookie-1989","name":"Clearly Retro Rated Rookie 1989","category":"insert","totalCards":4,"parallels":[{"name":"Platinum Holo","printRun":1}],"cards":[{"number":"1","player":"Anthony Richardson","team":"Indianapolis Colts"},{"number":"2","player":"Bryce Young","team":"Carolina Panthers"},{"number":"3","player":"C.J. Stroud","team":"Houston Texans"},{"number":"4","player":"Will Levis","team":"Tennessee Titans"}]},{"id":"clearly-the-rookies","name":"Clearly The Rookies","category":"insert","totalCards":15,"parallels":[{"name":"Mosaic Holo","printRun":null},{"name":"Red","printRun":100},{"name":"Green","printRun":49},{"name":"Silver Holo","printRun":25},{"name":"Gold Holo","printRun":10},{"name":"Platinum Holo","printRun":1}],"cards":[{"number":"1","player":"Anthony Richardson","team":"Indianapolis Colts"},{"number":"2","player":"Bijan Robinson","team":"Atlanta Falcons"},{"number":"3","player":"Jahmyr Gibbs","team":"Detroit Lions"},{"number":"4","player":"Jaxon Smith-Njigba","team":"Seattle Seahawks"},{"number":"5","player":"Quentin Johnston","team":"Los Angeles Chargers"},{"number":"6","player":"Zay Flowers","team":"Baltimore Ravens"},{"number":"7","player":"Jordan Addison","team":"Minnesota Vikings"},{"number":"8","player":"Hendon Hooker","team":"Detroit Lions"},{"number":"9","player":"Puka Nacua","team":"Los Angeles Rams"},{"number":"10","player":"Jayden Reed","team":"Green Bay Packers"},{"number":"11","player":"Rashee Rice","team":"Kansas City Chiefs"},{"number":"12","player":"C.J. Stroud","team":"Houston Texans"},{"number":"13","player":"Bryce Young","team":"Carolina Panthers"},{"number":"14","player":"Will Levis","team":"Tennessee Titans"},{"number":"15","player":"De’Von Achane","team":"Miami Dolphins"}]},{"id":"downtown","name":"Downtown","category":"insert","totalCards":30,"parallels":[{"name":"Platinum Holo","printRun":1}],"cards":[{"number":"1","player":"Aaron Rodgers","team":"New York Jets"},{"number":"2","player":"Anthony Richardson","team":"Indianapolis Colts"},{"number":"3","player":"Bijan Robinson","team":"Atlanta Falcons"},{"number":"4","player":"Bo Jackson","team":"Los Angeles Raiders"},{"number":"5","player":"Brett Favre","team":"Green Bay Packers"},{"number":"6","player":"Bryce Young","team":"Carolina Panthers"},{"number":"7","player":"C.J. Stroud","team":"Houston Texans"},{"number":"8","player":"Dan Marino","team":"Miami Dolphins"},{"number":"9","player":"Darrelle Revis","team":"New York Jets"},{"number":"10","player":"Davante Adams","team":"Las Vegas Raiders"},{"number":"11","player":"Derrick Henry","team":"Tennessee Titans"},{"number":"12","player":"Jahmyr Gibbs","team":"Detroit Lions"},{"number":"13","player":"Jalen Hurts","team":"Philadelphia Eagles"},{"number":"14","player":"Jaxon Smith-Njigba","team":"Seattle Seahawks"},{"number":"15","player":"Jerry Rice","team":"San Francisco 49ers"},{"number":"16","player":"Joe Burrow","team":"Cincinnati Bengals"},{"number":"17","player":"Joe Montana","team":"San Francisco 49ers"},{"number":"18","player":"Jonathan Taylor","team":"Indianapolis Colts"},{"number":"19","player":"Jordan Addison","team":"Minnesota Vikings"},{"number":"20","player":"Josh Jacobs","team":"Las Vegas Raiders"},{"number":"21","player":"Justin Fields","team":"Chicago Bears"},{"number":"22","player":"Michael Irvin","team":"Dallas Cowboys"},{"number":"23","player":"Najee Harris","team":"Pittsburgh Steelers"},{"number":"24","player":"Odell Beckham Jr.","team":"Baltimore Ravens"},{"number":"25","player":"Patrick Mahomes II","team":"Kansas City Chiefs"},{"number":"26","player":"Peyton Manning","team":"Indianapolis Colts"},{"number":"27","player":"Quentin Johnston","team":"Los Angeles Chargers"},{"number":"28","player":"Saquon Barkley","team":"New York Giants"},{"number":"29","player":"Will Levis","team":"Tennessee Titans"},{"number":"30","player":"Zay Flowers","team":"Baltimore Ravens"}]},{"id":"gridiron-marvels","name":"Gridiron Marvels","category":"insert","totalCards":20,"parallels":[{"name":"Platinum Holo","printRun":1}],"cards":[{"number":"1","player":"Amon-Ra St. Brown","team":"Detroit Lions"},{"number":"2","player":"Jalen Hurts","team":"Philadelphia Eagles"},{"number":"3","player":"Ja’Marr Chase","team":"Cincinnati Bengals"},{"number":"4","player":"Julius Peppers","team":"Carolina Panthers"},{"number":"5","player":"Justin Fields","team":"Chicago Bears"},{"number":"6","player":"Kurt Warner","team":"Arizona Cardinals"},{"number":"7","player":"Lamar Jackson","team":"Baltimore Ravens"},{"number":"8","player":"Patrick Mahomes II","team":"Kansas City Chiefs"},{"number":"9","player":"T.J. Watt","team":"Pittsburgh Steelers"},{"number":"10","player":"Tyreek Hill","team":"Miami Dolphins"},{"number":"11","player":"Anthony Richardson","team":"Indianapolis Colts"},{"number":"12","player":"Bijan Robinson","team":"Atlanta Falcons"},{"number":"13","player":"Bryce Young","team":"Carolina Panthers"},{"number":"14","player":"C.J. Stroud","team":"Houston Texans"},{"number":"15","player":"Jahmyr Gibbs","team":"Detroit Lions"},{"number":"16","player":"Jaxon Smith-Njigba","team":"Seattle Seahawks"},{"number":"17","player":"Jordan Addison","team":"Minnesota Vikings"},{"number":"18","player":"Puka Nacua","team":"Los Angeles Rams"},{"number":"19","player":"Will Levis","team":"Tennessee Titans"},{"number":"20","player":"Zay Flowers","team":"Baltimore Ravens"}]},{"id":"night-moves","name":"Night Moves","category":"insert","totalCards":25,"parallels":[{"name":"Platinum Holo","printRun":1}],"cards":[{"number":"1","player":"Aaron Rodgers","team":"New York Jets"},{"number":"2","player":"Christian McCaffrey","team":"San Francisco 49ers"},{"number":"3","player":"Cooper Kupp","team":"Los Angeles Rams"},{"number":"4","player":"DK Metcalf","team":"Seattle Seahawks"},{"number":"5","player":"Jared Goff","team":"Detroit Lions"},{"number":"6","player":"Joe Burrow","team":"Cincinnati Bengals"},{"number":"7","player":"Jordan Love","team":"Green Bay Packers"},{"number":"8","player":"Josh Allen","team":"Buffalo Bills"},{"number":"9","player":"Justin Fields","team":"Chicago Bears"},{"number":"10","player":"Justin Jefferson","team":"Minnesota Vikings"},{"number":"11","player":"Lamar Jackson","team":"Baltimore Ravens"},{"number":"12","player":"Maxx Crosby","team":"Las Vegas Raiders"},{"number":"13","player":"Nick Chubb","team":"Cleveland Browns"},{"number":"14","player":"Patrick Mahomes II","team":"Kansas City Chiefs"},{"number":"15","player":"Trevor Lawrence","team":"Jacksonville Jaguars"},{"number":"16","player":"Anthony Richardson","team":"Indianapolis Colts"},{"number":"17","player":"Bijan Robinson","team":"Atlanta Falcons"},{"number":"18","player":"Bryce Young","team":"Carolina Panthers"},{"number":"19","player":"C.J. Stroud","team":"Houston Texans"},{"number":"20","player":"De’Von Achane","team":"Miami Dolphins"},{"number":"21","player":"Hendon Hooker","team":"Detroit Lions"},{"number":"22","player":"Will Levis","team":"Tennessee Titans"},{"number":"23","player":"Jahmyr Gibbs","team":"Detroit Lions"},{"number":"24","player":"Zay Flowers","team":"Baltimore Ravens"},{"number":"25","player":"Puka Nacua","team":"Los Angeles Rams"}]},{"id":"nu-clear","name":"Nu-CLEAR","category":"insert","totalCards":18,"parallels":[{"name":"Platinum Holo","printRun":1}],"cards":[{"number":"1","player":"Aaron Rodgers","team":"New York Jets"},{"number":"2","player":"Jalen Hurts","team":"Philadelphia Eagles"},{"number":"3","player":"Joe Burrow","team":"Cincinnati Bengals"},{"number":"4","player":"Josh Allen","team":"Buffalo Bills"},{"number":"5","player":"Justin Jefferson","team":"Minnesota Vikings"},{"number":"6","player":"Micah Parsons","team":"Dallas Cowboys"},{"number":"7","player":"Nick Bosa","team":"San Francisco 49ers"},{"number":"8","player":"Patrick Mahomes II","team":"Kansas City Chiefs"},{"number":"9","player":"Anthony Richardson","team":"Indianapolis Colts"},{"number":"10","player":"Bijan Robinson","team":"Atlanta Falcons"},{"number":"11","player":"Bryce Young","team":"Carolina Panthers"},{"number":"12","player":"C.J. Stroud","team":"Houston Texans"},{"number":"13","player":"Jahmyr Gibbs","team":"Detroit Lions"},{"number":"14","player":"Jaxon Smith-Njigba","team":"Seattle Seahawks"},{"number":"15","player":"Jordan Addison","team":"Minnesota Vikings"},{"number":"16","player":"Quentin Johnston","team":"Los Angeles Chargers"},{"number":"17","player":"Will Levis","team":"Tennessee Titans"},{"number":"18","player":"Zay Flowers","team":"Baltimore Ravens"}]},{"id":"rookie-special","name":"Rookie Special","category":"insert","totalCards":4,"parallels":[{"name":"Base","printRun":null}],"cards":[{"number":"1","player":"Anthony Richardson / Bryce Young / C.J. Stroud","team":"Indianapolis Colts / Carolina Panthers / Houston Texans"},{"number":"2","player":"Jahmyr Gibbs / Bijan Robinson / De’Von Achane","team":"Detroit Lions / Atlanta Falcons / Miami Dolphins"},{"number":"3","player":"Jordan Addison / Marvin Mims / Jaxon Smith-Njigba","team":"Minnesota Vikings / Denver Broncos / Seattle Seahawks"},{"number":"4","player":"Puka Nacua / Zay Flowers / Jayden Reed","team":"Los Angeles Rams / Baltimore Ravens / Green Bay Packers"}]}]}